pylekiwi/__init__.py
pylekiwi/arm_controller.py
pylekiwi/base_controller.py
pylekiwi/camera_controller.py
pylekiwi/commands/__init__.py
pylekiwi/commands/__main__.py
pylekiwi/commands/cli.py
pylekiwi/commands/launch_host_controller.py
pylekiwi/commands/launch_leader.py
pylekiwi/commands/launch_web_ui.py
pylekiwi/commands/web_ui.py
pylekiwi/data/SO101/README.md
pylekiwi/data/SO101/assets/base_motor_holder_so101_v1.ply
pylekiwi/data/SO101/assets/base_so101_v2.ply
pylekiwi/data/SO101/assets/motor_holder_so101_base_v1.ply
pylekiwi/data/SO101/assets/motor_holder_so101_wrist_v1.ply
pylekiwi/data/SO101/assets/moving_jaw_so101_v1.ply
pylekiwi/data/SO101/assets/rotation_pitch_so101_v1.ply
pylekiwi/data/SO101/assets/sts3215_03a_no_horn_v1.ply
pylekiwi/data/SO101/assets/sts3215_03a_v1.ply
pylekiwi/data/SO101/assets/under_arm_so101_v1.ply
pylekiwi/data/SO101/assets/upper_arm_so101_v1.ply
pylekiwi/data/SO101/assets/waveshare_mounting_plate_so101_v2.ply
pylekiwi/data/SO101/assets/wrist_roll_follower_so101_v1.ply
pylekiwi/data/SO101/assets/wrist_roll_pitch_so101_v2.ply
pylekiwi/data/SO101/joints_properties.xml
pylekiwi/data/SO101/scene.xml
pylekiwi/data/SO101/so101_new_calib.urdf
pylekiwi/data/SO101/so101_new_calib.xml
pylekiwi/data/SO101/so101_old_calib.urdf
pylekiwi/data/SO101/so101_old_calib.xml
pylekiwi/key_listener.py
pylekiwi/models.py
pylekiwi/nodes.py
pylekiwi/py.typed
pylekiwi/settings.py
pylekiwi/smoother.py
pylekiwi-0.8.0.dist-info/WHEEL
pylekiwi-0.8.0.dist-info/entry_points.txt
pylekiwi-0.8.0.dist-info/METADATA
pylekiwi-0.8.0.dist-info/RECORD
