Metadata-Version: 2.3
Name: pylekiwi
Version: 0.8.0
Summary: Python package for controlling the LeKiwi robot
Author: neka-nat
Author-email: neka-nat <nekanat.stock@gmail.com>
Requires-Dist: eclipse-zenoh>=1.5.1
Requires-Dist: gunicorn>=23.0.0
Requires-Dist: kinpy>=0.5.5
Requires-Dist: loguru>=0.7.3
Requires-Dist: mesop>=1.1.0
Requires-Dist: numpy>=1.26.4
Requires-Dist: opencv-python-headless>=4.11.0.86
Requires-Dist: pydantic>=2.11.10
Requires-Dist: rustypot>=1.3.0
Requires-Dist: typer>=0.19.2
Requires-Dist: pynput>=1.8.1 ; extra == 'client'
Requires-Dist: rerun-sdk>=0.28.1 ; extra == 'client'
Requires-Python: >=3.11
Provides-Extra: client
